video_dataset/__init__.py
video_dataset/annotations.py
video_dataset/dataset.py
video_dataset/padder.py
video_dataset/preprocessor.py
video_dataset/utils.py
video_dataset/video.py
video_dataset-0.3.0.dist-info/LICENSE
video_dataset-0.3.0.dist-info/METADATA
video_dataset-0.3.0.dist-info/WHEEL
video_dataset-0.3.0.dist-info/RECORD
