Metadata-Version: 2.3
Name: video-dataset
Version: 0.3.0
Summary: A pytorch compatible video dataset that is fully customizable.
Keywords: pytorch-video-dataset,pytorch,video-dataset
Author: raideno56
Author-email: nadirkichou@hotmail.fr
Maintainer: raideno56
Maintainer-email: nadirkichou@hotmail.fr
Requires-Python: >=3.12
Classifier: Programming Language :: Python :: 3
Classifier: Programming Language :: Python :: 3.12
Classifier: Programming Language :: Python :: 3.13
Requires-Dist: numpy (>=1.9.0)
Requires-Dist: opencv-python (>=4.11.0.86,<5.0.0.0)
Requires-Dist: pillow (>=11.1.0,<12.0.0)
Requires-Dist: pydantic (>=2.10.6,<3.0.0)
